praasper/__init__.py
praasper/cvt.py
praasper/phon_boundary.py
praasper/post_process.py
praasper/process.py
praasper/select_word.py
praasper/tool.py
praasper/utils.py
praasper/word_boundary.py
praasper/VAD/__init__.py
praasper/VAD/core_auto.py
praasper/VAD/tool_auto.py
praasper-0.4.5.dist-info/LICENSE
praasper-0.4.5.dist-info/METADATA
praasper-0.4.5.dist-info/WHEEL
praasper-0.4.5.dist-info/top_level.txt
praasper-0.4.5.dist-info/RECORD
