Metadata-Version: 2.1
Name: praasper
Version: 0.4.5
Summary: VAD-Enhanced ASR Framework for Researchers
Home-page: https://github.com/ParadeLuxe/Praasper
Author: Tony Liu
Author-email: paradeluxe3726@gmail.com
License: MIT
Classifier: Programming Language :: Python :: 3
Classifier: Operating System :: OS Independent
Requires-Python: >=3.10
License-File: LICENSE
Requires-Dist: textgrid
Requires-Dist: librosa
Requires-Dist: praat-parselmouth
Requires-Dist: funasr
Requires-Dist: torch
Requires-Dist: torchaudio
Requires-Dist: transformers
Requires-Dist: accelerate
